CHANGES.txt
MANIFEST.in
README.md
README.txt
setup.py
placevent/__init__.py
placevent/placevent.py
placevent.egg-info/PKG-INFO
placevent.egg-info/SOURCES.txt
placevent.egg-info/dependency_links.txt
placevent.egg-info/requires.txt
placevent.egg-info/top_level.txt
placevent/tests/__init__.py
placevent/tests/1L2Y/1L2Y.O.1.dx
placevent/tests/1L2Y/O_test.pdb
placevent/tests/1L2Y/__init__.py
placevent/tests/1L2Y/diffs
placevent/tests/1L2Y/placevent_test.sh
placevent/tests/1L2Y/ref/O.pdb
placevent/tests/1L2Y/ref/__init__.py
placevent/tests/1L2Y/test/O.pdb
ppdb/__init__.py
ppdb/pdb.py