Metadata-Version: 1.1
Name: placevent
Version: 1.4
Summary: Placevent solvent placement software
Home-page: http://dansindhikara.com/Software/Entries/2012/6/22_Placevent_New.html
Author: Daniel J. Sindhikara
Author-email: sindhikara@gmail.com
License: GPL
Download-URL: http://dansindhikara.com/Software/Entries/2012/6/22_Placevent_New.html
Platform: UNKNOWN
